cerebro/__init__.py
cerebro/cerebro_service.py
Muserk_cerebro-0.0.6.dist-info/METADATA
Muserk_cerebro-0.0.6.dist-info/WHEEL
Muserk_cerebro-0.0.6.dist-info/top_level.txt
Muserk_cerebro-0.0.6.dist-info/RECORD
