Metadata-Version: 2.1
Name: Muserk-cerebro
Version: 0.0.6
Summary: Muserk's distributed-computing management system
Home-page: https://github.com/Muserk-team/cerebro
Author: Muserk Dev
Author-email: dev@muserk.com
License: UNKNOWN
Platform: UNKNOWN
Classifier: Programming Language :: Python :: 3
Classifier: License :: OSI Approved :: MIT License
Classifier: Operating System :: OS Independent
